ai_sdk/__init__.py
ai_sdk/anthropic/__init__.py
ai_sdk/anthropic/chat_model.py
ai_sdk/anthropic/provider.py
ai_sdk/core/__init__.py
ai_sdk/core/errors.py
ai_sdk/core/generate_object.py
ai_sdk/core/generate_text.py
ai_sdk/core/language_model.py
ai_sdk/core/retry_strategy.py
ai_sdk/core/tool_calls.py
ai_sdk/core/types.py
ai_sdk/core/utils.py
ai_sdk/openai/__init__.py
ai_sdk/openai/chat_model.py
ai_sdk/openai/provider.py
genaix-0.1.0.dist-info/METADATA
genaix-0.1.0.dist-info/WHEEL
genaix-0.1.0.dist-info/RECORD
