Metadata-Version: 2.3
Name: genaix
Version: 0.1.0
Summary: A unified interface for working with different AI language model providers
License: MIT
Keywords: ai,sdk,language-models,machine-learning,nlp
Author: Jacques
Author-email: jverre@gmail.com
Requires-Python: >=3.9
Classifier: Development Status :: 3 - Alpha
Classifier: Intended Audience :: Developers
Classifier: License :: OSI Approved :: MIT License
Classifier: Programming Language :: Python :: 3
Classifier: Programming Language :: Python :: 3.9
Classifier: Programming Language :: Python :: 3.10
Classifier: Programming Language :: Python :: 3.11
Classifier: Programming Language :: Python :: 3.12
Classifier: Programming Language :: Python :: 3.13
Classifier: Topic :: Scientific/Engineering :: Artificial Intelligence
Classifier: Topic :: Software Development :: Libraries :: Python Modules
Requires-Dist: anthropic (>=0.49.0,<0.50.0)
Requires-Dist: httpx (>=0.28.1,<0.29.0)
Requires-Dist: pydantic (>=2.10.6,<3.0.0)
Requires-Dist: validators (>=0.34.0,<0.35.0)
Project-URL: Homepage, https://github.com/jverre/ai-sdk
Project-URL: Repository, https://github.com/jverre/ai-sdk
